mail_office.py
mail_office-0.2.0.dist-info/WHEEL
mail_office-0.2.0.dist-info/METADATA
mail_office-0.2.0.dist-info/RECORD
