Metadata-Version: 2.1
Name: mail-office
Version: 0.2.0
Summary: 
License: MIT
Author: mikki
Author-email: mikki@gmail.com
Requires-Python: >=3.9,<4.0
Classifier: License :: OSI Approved :: MIT License
Classifier: Programming Language :: Python :: 3
Classifier: Programming Language :: Python :: 3.9
Requires-Dist: Django (>=3.2,<4.0)
